{
  "run_timestamp": "20260323_225921",
  "dataframe_name": "df_feat",
  "best_horizon": 1,
  "best_model_name": "manual_stacking_rf_et",
  "ensemble_used": false,
  "stacking_used": true,
  "ensemble_members": [
    "rf",
    "et"
  ],
  "best_params": {
    "rf": {
      "class_weight": "balanced",
      "max_depth": 12,
      "max_features": "sqrt",
      "min_samples_leaf": 15,
      "n_estimators": 800,
      "n_jobs": -1,
      "random_state": 42
    },
    "et": {
      "class_weight": "balanced",
      "max_depth": 12,
      "max_features": "sqrt",
      "min_samples_leaf": 15,
      "n_estimators": 800,
      "n_jobs": -1,
      "random_state": 42
    }
  },
  "best_top_k": 40,
  "best_n_features": 40,
  "best_features": [
    "atl_hour",
    "xau_close_position",
    "xau_body_ratio",
    "atl_hour_sin",
    "atl_hour_cos",
    "trend_strength_20",
    "xau_rsi_14",
    "xau_direction",
    "xau_low",
    "london_move",
    "position_in_daily_range",
    "month_of_year",
    "xau_body",
    "day_of_week_cos",
    "day_of_week_sin",
    "xau_lower_wick",
    "day_of_week_num",
    "xau_ma_5",
    "xau_volatility_10",
    "dist_to_high_24",
    "bullish_streak_5",
    "xau_atr_14",
    "dist_to_low_24",
    "volatility_regime",
    "xau_bullish_count_5",
    "atr_regime",
    "xau_dir_lag_3_num",
    "range_compression_20",
    "xau_dir_num_lag_3",
    "london_session_return",
    "xau_ma_10_slope",
    "xau_bearish_count_5",
    "pre_ny_momentum",
    "xau_ma_dist_10",
    "bearish_streak_5",
    "xau_return_lag_1",
    "pre_ny_return_6",
    "xau_direction_lag_1",
    "date_of_month_cos",
    "xau_return_5"
  ],
  "keep_collinear_features": true,
  "signal_prefilter_keep": 80,
  "final_metrics": {
    "accuracy": 0.5121343085106383,
    "balanced_accuracy": 0.5152329219222764,
    "precision": 0.5388110072689511,
    "recall": 0.4414548548335638,
    "f1": 0.4852984158531595,
    "roc_auc": 0.5204030290223387,
    "log_loss": 0.6926610742904129
  },
  "train_rows": 84221,
  "val_rows": 18048,
  "test_rows": 18048,
  "time_start_utc": "2006-03-19 20:00:00+00:00",
  "time_end_utc": "2026-03-24 00:00:00+00:00",
  "available_model_families": [
    "et",
    "hgb",
    "rf",
    "xgb"
  ],
  "xgboost_available": true
}